py2vtk/__init__.py
py2vtk/_version.py
py2vtk/api/__init__.py
py2vtk/api/parallel.py
py2vtk/api/serial.py
py2vtk/core/__init__.py
py2vtk/core/evtk.py
py2vtk/core/vtkcells.py
py2vtk/core/vtkfiles.py
py2vtk/core/xml.py
py2vtk/dask/__init__.py
py2vtk/mpi/__init__.py
py2vtk/mpi/api.py
py2vtk/utilities/__init__.py
py2vtk/utilities/utils.py
tests/test_api.py
tests/test_core.py
tests/test_mpi.py
tests/utils_test.py
py2vtk-1.1.dist-info/LICENSE
py2vtk-1.1.dist-info/METADATA
py2vtk-1.1.dist-info/WHEEL
py2vtk-1.1.dist-info/top_level.txt
py2vtk-1.1.dist-info/RECORD
