Metadata-Version: 2.1
Name: py2vtk
Version: 1.1
Summary: Low dependency module to export to VTK from python
Home-page: https://github.com/anlavandier/py2vtk
Author: Antoine Lavandier
Author-email: antoine.lavandier.24.11@gmail.com
License: MIT
Keywords: Visualization VTK
Requires-Python: >=3.7
License-File: LICENSE
Requires-Dist: numpy
Provides-Extra: doc
Requires-Dist: sphinx ; extra == 'doc'
Requires-Dist: sphinx-rtd-theme ; extra == 'doc'
Provides-Extra: mpi
Requires-Dist: mpi4py ; extra == 'mpi'
Provides-Extra: tests
Requires-Dist: pytest ; extra == 'tests'
Requires-Dist: vtk ; extra == 'tests'
Requires-Dist: mpi4py ; extra == 'tests'
